rotarex_api/__init__.py
rotarex_api/api.py
rotarex_api/exceptions.py
rotarex_api-0.1.0.dist-info/licenses/LICENSE
rotarex_api-0.1.0.dist-info/METADATA
rotarex_api-0.1.0.dist-info/WHEEL
rotarex_api-0.1.0.dist-info/top_level.txt
rotarex_api-0.1.0.dist-info/RECORD
